better_log/__init__.py
better_log/handler.py
better_log-0.0.2.dist-info/LICENSE
better_log-0.0.2.dist-info/METADATA
better_log-0.0.2.dist-info/WHEEL
better_log-0.0.2.dist-info/top_level.txt
better_log-0.0.2.dist-info/RECORD
