Metadata-Version: 2.1
Name: better-log
Version: 0.0.2
Summary: a better log
Home-page: https://github.com/iammyz/better_log
Author: mengyunzhuo
Author-email: 282053798@qq.com
License: MIT
Keywords: log python
Platform: UNKNOWN
Classifier: Development Status :: 4 - Beta
Classifier: Intended Audience :: Developers
Classifier: Topic :: Software Development :: Build Tools
Classifier: License :: OSI Approved :: MIT License
Classifier: Programming Language :: Python :: 3.6
Classifier: Programming Language :: Python :: 3.7
Classifier: Programming Language :: Python :: 3.8
Classifier: Programming Language :: Python :: 3.9
Classifier: Programming Language :: Python :: 3.10
License-File: LICENSE
